{"id":136,"code":"308","last_update":"2019-09-12T07:45:05+0300","category_id":3,"name":"Gamma-tocopherol","status":"Safe","veg":"0","function":"antioxidant","foods":"Found in most foods, it is abundant in, amongst other things, whole grain cereals, corn and cottonseed oils, egg yolks, meat and milk.","notice":"May come from Genetically Modified sources.","info":"Vitamin E, known as the anti-sterility vitamin. E308 is an antioxidant for polyunsaturated fatty acids as well as a vitamin.","url":"http:\/\/e-additives.herokuapp.com\/additives\/308"}
